mcp_clients/__init__.py
mcp_clients/gemini_client.py
mcp_clients/openai_client.py
mcp_clients/version.py
mcp_clients-0.0.4.dist-info/METADATA
mcp_clients-0.0.4.dist-info/WHEEL
mcp_clients-0.0.4.dist-info/RECORD
