Metadata-Version: 2.4
Name: mcp-clients
Version: 0.0.4
Summary: Model Context Protocol Clients SDK
Project-URL: Repository, https://github.com/faizrazadec/mcp_clients
Project-URL: Issues, https://github.com/faizrazadec/mcp_clients/issues
Author-email: Muhammad Faiz Raza <faiz.raza.dec@gmail.com>
Maintainer-email: Muhammad Faiz Raza <faiz.raza.dec@gmail.com>
License: MIT
Keywords: automation,git,llm,mcp,mcp-clients,tools
Classifier: Development Status :: 4 - Beta
Classifier: Intended Audience :: Developers
Classifier: License :: OSI Approved :: MIT License
Classifier: Programming Language :: Python :: 3
Classifier: Programming Language :: Python :: 3.12
Classifier: Programming Language :: Python :: 3.13
Requires-Python: >=3.12
Requires-Dist: google-genai>=1.23.0
Requires-Dist: mcp>=1.10.1
Requires-Dist: openai>=1.93.0
